synergypay/__init__.py
synergypay/core.py
synergypay-0.1.1.dist-info/licenses/LICENSE
synergypay-0.1.1.dist-info/METADATA
synergypay-0.1.1.dist-info/WHEEL
synergypay-0.1.1.dist-info/top_level.txt
synergypay-0.1.1.dist-info/RECORD
