Metadata-Version: 2.4
Name: synergypay
Version: 0.1.1
Summary: Web3 payment SDK for Synergetics platform
Author-email: Synergetics <anurag.s@synergetics.ai>
Maintainer-email: Synergetics <anurag.s@synergetics.ai>
License-Expression: MIT
Project-URL: Homepage, https://github.com/synergeticsai/synergypay
Project-URL: Repository, https://github.com/synergeticsai/synergypay
Project-URL: Documentation, https://docs.synergetics.ai/synergypay
Project-URL: Bug Tracker, https://github.com/synergeticsai/synergypay/issues
Keywords: web3,blockchain,payments,ethereum,synergetics,crypto
Classifier: Development Status :: 4 - Beta
Classifier: Intended Audience :: Developers
Classifier: Programming Language :: Python :: 3
Classifier: Programming Language :: Python :: 3.8
Classifier: Programming Language :: Python :: 3.9
Classifier: Programming Language :: Python :: 3.10
Classifier: Programming Language :: Python :: 3.11
Classifier: Programming Language :: Python :: 3.12
Classifier: Topic :: Software Development :: Libraries :: Python Modules
Classifier: Topic :: Office/Business :: Financial
Classifier: Topic :: Internet :: WWW/HTTP :: Dynamic Content
Classifier: Operating System :: OS Independent
Requires-Python: >=3.8
License-File: LICENSE
Requires-Dist: web3>=6.0.0
Requires-Dist: eth-account>=0.8.0
Requires-Dist: requests>=2.28.0
Requires-Dist: httpx>=0.24.0
Requires-Dist: python-dotenv>=1.0.0
Requires-Dist: pydantic>=2.0.0
Provides-Extra: dev
Requires-Dist: pytest>=7.0.0; extra == "dev"
Requires-Dist: pytest-asyncio>=0.21.0; extra == "dev"
Requires-Dist: black>=23.0.0; extra == "dev"
Requires-Dist: flake8>=6.0.0; extra == "dev"
Requires-Dist: mypy>=1.0.0; extra == "dev"
Dynamic: license-file
